{"files":{"packages/core/dist":{"size":0,"mtime_nanos":0,"mode":0,"is_dir":true},"packages/core/dist/index.d.cts":{"size":5542,"mtime_nanos":1783094464443795700,"mode":420,"is_dir":false},"packages/core/dist/index.cjs":{"size":6605,"mtime_nanos":1783094463000583700,"mode":420,"is_dir":false},"packages/core/.turbo/turbo-build.log":{"size":620,"mtime_nanos":1783094464511852700,"mode":420,"is_dir":false},"packages/core/dist/index.d.ts":{"size":5542,"mtime_nanos":1783094464443795700,"mode":420,"is_dir":false},"packages/core/dist/index.js":{"size":5328,"mtime_nanos":1783094463000583700,"mode":420,"is_dir":false}},"order":["packages/core/.turbo/turbo-build.log","packages/core/dist","packages/core/dist/index.cjs","packages/core/dist/index.d.cts","packages/core/dist/index.d.ts","packages/core/dist/index.js"]}